imgrs-0.3.8.dist-info/METADATA
imgrs-0.3.8.dist-info/WHEEL
imgrs-0.3.8.dist-info/licenses/LICENSE
imgrs/__init__.py
imgrs/_core.pyd
imgrs/enums.py
imgrs/image.py
imgrs/imagefont.py
imgrs/mixins/__init__.py
imgrs/mixins/blending_mixin.py
imgrs/mixins/color_mixin.py
imgrs/mixins/core_mixin.py
imgrs/mixins/drawing_mixin.py
imgrs/mixins/effects_mixin.py
imgrs/mixins/filters/__init__.py
imgrs/mixins/filters/artistic_filters.py
imgrs/mixins/filters/auto_enhance_filters.py
imgrs/mixins/filters/basic_filters.py
imgrs/mixins/filters/blur_filters.py
imgrs/mixins/filters/color_filters.py
imgrs/mixins/filters/composite_filters.py
imgrs/mixins/filters/css_filters.py
imgrs/mixins/filters/edge_filters.py
imgrs/mixins/filters/morphological_filters.py
imgrs/mixins/filters/noise_filters.py
imgrs/mixins/filters/sharpen_filters.py
imgrs/mixins/filters/stylistic_filters.py
imgrs/mixins/filters_combined.py
imgrs/mixins/metadata_mixin.py
imgrs/mixins/pixel_mixin.py
imgrs/mixins/text_mixin.py
imgrs/mixins/transform_mixin.py
imgrs/operations.py
imgrs-0.3.8.dist-info/RECORD
