Metadata-Version: 2.4
Name: imgrs
Version: 0.3.8
Classifier: Development Status :: 4 - Beta
Classifier: Intended Audience :: Developers
Classifier: License :: OSI Approved :: Apache Software License
Classifier: Programming Language :: Python :: 3
Classifier: Programming Language :: Python :: 3.8
Classifier: Programming Language :: Python :: 3.9
Classifier: Programming Language :: Python :: 3.10
Classifier: Programming Language :: Python :: 3.11
Classifier: Programming Language :: Python :: 3.12
Classifier: Programming Language :: Python :: 3.13
Classifier: Programming Language :: Rust
Classifier: Topic :: Multimedia :: Graphics
Classifier: Topic :: Multimedia :: Graphics :: Graphics Conversion
Classifier: Topic :: Software Development :: Libraries :: Python Modules
Classifier: Operating System :: OS Independent
Requires-Dist: numpy>=1.20.0 ; extra == 'numpy'
Requires-Dist: numpy>=1.20.0 ; extra == 'full'
Requires-Dist: pytest>=7.0 ; extra == 'dev'
Requires-Dist: pytest-benchmark>=4.0 ; extra == 'dev'
Requires-Dist: pillow>=9.0 ; extra == 'dev'
Requires-Dist: numpy>=1.20.0 ; extra == 'dev'
Provides-Extra: numpy
Provides-Extra: full
Provides-Extra: dev
License-File: LICENSE
Summary: A modern, high-performance image processing library for Python, powered by Rust.
Keywords: image,processing,pillow,rust,performance,filters,text
Author-email: Ebtisam Jubair <>
License: Apache-2.0
Requires-Python: >=3.8
Project-URL: Homepage, https://github.com/grandpaej/imgrs
Project-URL: Repository, https://github.com/grandpaej/imgrs
Project-URL: Documentation, https://grandpaej.github.io/imgrs
Project-URL: Issues, https://github.com/grandpaej/imgrs/issues
Project-URL: Changelog, https://github.com/grandpaej/imgrs/blob/main/CHANGELOG.md
